LICENSE
MANIFEST.in
README.md
README.txt
setup.py
airflow/__init__.py
airflow/providers/__init__.py
airflow/providers/zeppelin/PythonUtils.py
airflow/providers/zeppelin/Zeppelin.py
airflow/providers/zeppelin/__init__.py
airflow/providers/zeppelin/hooks/ZeppelinHook.py
airflow/providers/zeppelin/hooks/__init__.py
airflow/providers/zeppelin/operators/ZeppelinOperator.py
airflow/providers/zeppelin/operators/__init__.py
airflow_providers_zeppelin.egg-info/PKG-INFO
airflow_providers_zeppelin.egg-info/SOURCES.txt
airflow_providers_zeppelin.egg-info/dependency_links.txt
airflow_providers_zeppelin.egg-info/requires.txt
airflow_providers_zeppelin.egg-info/top_level.txt