Metadata-Version: 1.1
Name: airflow-providers-zeppelin
Version: 0.0.1
Summary: Provider package airflow-providers-zeppelin for Apache Airflow.
Home-page: https://github.com/whiterxine/airflow-providers-zeppelin
Author: LiuJie
Author-email: whiterxine@163.com
License: MIT
Platform: UNKNOWN
Classifier: License :: OSI Approved :: MIT License
Classifier: Programming Language :: Python
Classifier: Programming Language :: Python :: 3
Classifier: Programming Language :: Python :: 3.6
Classifier: Programming Language :: Python :: Implementation :: CPython
Classifier: Programming Language :: Python :: Implementation :: PyPy
